Metadata-Version: 1.0
Name: kfinny.avclass
Version: 3.0
Summary: A package for malicialab's avclass
Home-page: https://github.com/kfinny/avclass-lib
Author: Kevin Finnigin
Author-email: kevin@finnigin.net
License: MIT
Platform: UNKNOWN
